parametrized.py
pytest_parametrized-1.7.dist-info/LICENSE.txt
pytest_parametrized-1.7.dist-info/METADATA
pytest_parametrized-1.7.dist-info/WHEEL
pytest_parametrized-1.7.dist-info/top_level.txt
pytest_parametrized-1.7.dist-info/RECORD
