Metadata-Version: 2.1
Name: pytest-parametrized
Version: 1.7
Summary: Pytest decorator for parametrizing tests with default iterables.
Author-email: Aric Coady <aric.coady@gmail.com>
License: Copyright 2022 Aric Coady
Project-URL: Homepage, https://github.com/coady/pytest-parametrized
Project-URL: Changelog, https://github.com/coady/pytest-parametrized/blob/main/CHANGELOG.md
Project-URL: Issues, https://github.com/coady/pytest-parametrized/issues
Keywords: pytest,parametrize,parameterize,fixture
Classifier: Development Status :: 5 - Production/Stable
Classifier: Framework :: Pytest
Classifier: Intended Audience :: Developers
Classifier: License :: OSI Approved :: Apache Software License
Classifier: Operating System :: OS Independent
Classifier: Programming Language :: Python :: 3
Classifier: Programming Language :: Python :: 3.10
Classifier: Programming Language :: Python :: 3.11
Classifier: Programming Language :: Python :: 3.12
Classifier: Programming Language :: Python :: 3.13
Classifier: Programming Language :: Python :: 3.14
Classifier: Topic :: Software Development :: Testing
Requires-Python: >=3.10
License-File: LICENSE.txt
Requires-Dist: pytest
